{"sections":{"17242332875de99409":{"type":"apps","disabled":true,"settings":{"include_margins":true}},"main_slideshow_ixkrj9":{"type":"main-slideshow","blocks":{"slide_rXgwcn":{"type":"slide","disabled":true,"settings":{"image":"shopify:\/\/shop_images\/1200x796_3_ad742389-5c92-4937-b2ff-09b9459cbcae.webp","desktop_image":"shopify:\/\/shop_images\/2400x735__2_7673bff9-4364-48ac-8991-d873d136653a.webp","heading":"","heading_size":"h1","subheading":"","button_label":"","link":"shopify:\/\/collections\/health-reset-sale","button_style_secondary":false,"box_align":"middle-center","show_text_box":false,"text_alignment":"center","image_overlay_opacity":0,"color_scheme":"scheme-1","text_alignment_mobile":"center"}},"slide_3wAXjb":{"type":"slide","settings":{"image":"shopify:\/\/shop_images\/1200x796_3.jpg","desktop_image":"shopify:\/\/shop_images\/2400_x_735_main.jpg","heading":"","heading_size":"h1","subheading":"","button_label":"","link":"shopify:\/\/collections\/all-products","button_style_secondary":false,"box_align":"middle-center","show_text_box":false,"text_alignment":"center","image_overlay_opacity":0,"color_scheme":"scheme-1","text_alignment_mobile":"center"}},"slide_kR7KfW":{"type":"slide","disabled":true,"settings":{"image":"shopify:\/\/shop_images\/720_300_f63b8208-5853-4214-b2a8-4f1a393d3237.jpg","desktop_image":"shopify:\/\/shop_images\/1600x380_89bdff40-8b69-4523-875d-c05234cffcc5.jpg","heading":"","heading_size":"h1","subheading":"","button_label":"","link":"shopify:\/\/collections\/buy-3-pay-for-the-2","button_style_secondary":false,"box_align":"middle-center","show_text_box":false,"text_alignment":"center","image_overlay_opacity":0,"color_scheme":"","text_alignment_mobile":"center"}},"slide_D4VKM4":{"type":"slide","disabled":true,"settings":{"image":"shopify:\/\/shop_images\/1200x796_1_beb640ae-0134-4c8d-a948-cc28703898b3.webp","desktop_image":"shopify:\/\/shop_images\/diwali.webp","heading":"","heading_size":"h1","subheading":"","button_label":"","link":"shopify:\/\/collections\/collections-all-products","button_style_secondary":false,"box_align":"middle-center","show_text_box":false,"text_alignment":"center","image_overlay_opacity":0,"color_scheme":"scheme-1","text_alignment_mobile":"center"}}},"block_order":["slide_rXgwcn","slide_3wAXjb","slide_kR7KfW","slide_D4VKM4"],"settings":{"layout":"full_bleed","slide_height":"adapt_image","slider_visual":"counter","auto_rotate":false,"change_slides_speed":5,"image_behavior":"none","show_text_below":true,"accessibility_info":"Slideshow about our brand"}},"custom_liquid_3Gd3AG":{"type":"custom-liquid","disabled":true,"name":"t:sections.custom-liquid.presets.name","settings":{"custom_liquid":"<div class=\"countdown-outer\">\n  <div class=\"countdown-container\">\n    <div class=\"countdown-left\">\n      <h3>THE FINAL 24 HOURS | Popular Picks Selling Out!<\/h3>\n      <h3 class=\"last-day-text\">LAST DAY TO SAVE 30%<\/h3>\n    <\/div>\n    <div class=\"countdown-right\">\n      {% render 'page-timer-clock' %}\n    <\/div>\n  <\/div>\n<\/div>\n\n<style>\n  .countdown-outer { background: #26463c; }\n  .offer-banner-bogo img { display: block; }\n  \n  .countdown-container {\n    display: grid;\n    grid-template-columns: 1fr auto;\n    align-items: center;\n    gap: 20px;\n    padding: 10px 20px;\n  }\n  \n  .countdown-left {\n    display: flex;\n    flex-direction: column;\n    gap: 5px;\n  }\n  \n  .countdown-left h3 {\n    margin: 0;\n  }\n  \n  .countdown-right {\n    display: flex;\n    align-items: center;\n  }\n  \n  @media (max-width: 750px) {\n    .countdown-container {\n      grid-template-columns: 1fr;\n      text-align: center;\n    }\n    .countdown-right {\n      justify-content: center;\n    }\n    .timer-container { margin: 10px 0; }\n  }\n\n  \/* Urgency Animation *\/\n  .countdown-container h3 span {\n    display: inline-block;\n    color: #ff6b35;\n    font-weight: bold;\n    animation: urgentPulse 1.2s ease-in-out infinite;\n    text-shadow: 0 0 8px rgba(255, 107, 53, 0.6);\n  }\n\n  @keyframes urgentPulse {\n    0% { \n      opacity: 1; \n      transform: scale(1);\n      color: #ff6b35;\n    }\n    50% { \n      opacity: 0.7; \n      transform: scale(1.05);\n      color: #ff4500;\n      text-shadow: 0 0 15px rgba(255, 69, 0, 0.8);\n    }\n    100% { \n      opacity: 1; \n      transform: scale(1);\n      color: #ff6b35;\n    }\n  }\n\n  .countdown-container h3 span:hover {\n    animation: urgentShake 0.5s ease-in-out infinite;\n  }\n\n  @keyframes urgentShake {\n    0%, 100% { transform: translateX(0); }\n    25% { transform: translateX(-2px); }\n    75% { transform: translateX(2px); }\n  }\n<\/style>","color_scheme":"","padding_top":0,"padding_bottom":0}},"menu":{"type":"metaobject-collection-menu","settings":{}},"banner":{"type":"main-collection-banner","disabled":true,"settings":{"show_collection_description":true,"show_collection_image":false,"color_scheme":"scheme-1"}},"old_product_single_banner_VyDAMK":{"type":"old-product-single-banner","disabled":true,"settings":{"title":"","image":"shopify:\/\/shop_images\/GHEE_RANGE_DARK.jpg","mobimg":"shopify:\/\/shop_images\/GHEE_RANGE_DARK_720-300.jpg","background":""}},"old_product_single_banner_G8rFyD":{"type":"old-product-single-banner","disabled":true,"settings":{"title":"","image":"shopify:\/\/shop_images\/GHEE_RANGE_LIGHT.jpg","mobimg":"shopify:\/\/shop_images\/GHEE_RANGE_LIGHT_720-300.jpg","background":""}},"main_slideshow_iM8cgk":{"type":"main-slideshow","blocks":{"slide_C3CUKN":{"type":"slide","disabled":true,"settings":{"image":"shopify:\/\/shop_images\/720x200.jpg","desktop_image":"shopify:\/\/shop_images\/1600x380.jpg","heading":"","heading_size":"h1","subheading":"","button_label":"","link":"shopify:\/\/collections\/buy-3-pay-for-the-2","button_style_secondary":false,"box_align":"middle-center","show_text_box":false,"text_alignment":"center","image_overlay_opacity":0,"color_scheme":"","text_alignment_mobile":"center"}}},"block_order":["slide_C3CUKN"],"settings":{"layout":"full_bleed","slide_height":"adapt_image","slider_visual":"counter","auto_rotate":false,"change_slides_speed":5,"image_behavior":"none","show_text_below":true,"accessibility_info":"Slideshow about our brand"}},"product-grid":{"type":"metaobject-collection-data-list","settings":{"products_per_page":16,"columns_desktop":5,"color_scheme":"scheme-1","image_ratio":"adapt","image_shape":"default","show_secondary_image":true,"show_vendor":false,"show_rating":true,"quick_add":"standard","columns_mobile":"2","padding_top":36,"padding_bottom":36}}},"order":["17242332875de99409","main_slideshow_ixkrj9","custom_liquid_3Gd3AG","menu","banner","old_product_single_banner_VyDAMK","old_product_single_banner_G8rFyD","main_slideshow_iM8cgk","product-grid"]}